furiosa_quantizer_impl-0.10.1.dist-info/METADATA
furiosa_quantizer_impl-0.10.1.dist-info/WHEEL
furiosa_quantizer_impl-0.10.1.dist-info/license_files/LICENSE
furiosa_quantizer_impl.libs/libonnxruntime-0ed2d90b.so.1.15.1
furiosa_quantizer_impl.libs/libnpu-2a4f9dd0.so
furiosa_quantizer_impl/__init__.py
furiosa_quantizer_impl/furiosa_quantizer_impl.cpython-310-x86_64-linux-gnu.so
furiosa_quantizer_impl-0.10.1.dist-info/RECORD
